<Request Id="1" Version="1.0">
<Header>
  <Authentication>
	<AccessKeyID>11F3242118FF2ADD5D117CBF216F29AC578F6BA6</AccessKeyID>
	<AuthMethod>CXAuth</AuthMethod>
	<CXUserName>admin</CXUserName>
	<AccessSignature></AccessSignature>
  </Authentication>
</Header>
<Body>
  <FunctionRequest Name="GetProtectionState">
	<Parameter Name="ProtectionPlanId" Value="3"/>
	<ParameterGroup Id="Servers"> <!-- If provided, should return the protection stage only for this server -->
		<Parameter Name="SourceHostId1" Value="2A65CF56-7A09-9645-90BCB8D6CF19CE65" /> 
		<Parameter Name="SourceHostId2" Value="AD65CF56-7A09-9645-90BCB8D6CF19CE65" />
	</ParameterGroup>
  </FunctionRequest>
</Body>
</Request>
